waveshare_transparent_oled/__init__.py
waveshare_transparent_oled/oled_driver.py
waveshare_transparent_oled-1.0.5.dist-info/licenses/LICENSE
waveshare_transparent_oled-1.0.5.dist-info/METADATA
waveshare_transparent_oled-1.0.5.dist-info/WHEEL
waveshare_transparent_oled-1.0.5.dist-info/top_level.txt
waveshare_transparent_oled-1.0.5.dist-info/RECORD
