Metadata-Version: 2.4
Name: waveshare-transparent-oled
Version: 1.0.5
Summary: Driver for Waveshare 1.51-inch Transparent OLED (128x64, blue) for Raspberry Pi
Author-email: Asray Gopa <asraygopa@gmail.com>
License: Copyright 2025 Asray Gopa
Project-URL: Homepage, https://github.com/asrayg/waveshare_transparent_screen_driver/
Project-URL: Issues, https://github.com/asrayg/waveshare_transparent_screen_driver/issues
Keywords: waveshare,oled,raspberry-pi,transparent display,ssd1309,spi,embedded
Classifier: Development Status :: 4 - Beta
Classifier: License :: OSI Approved :: MIT License
Classifier: Programming Language :: Python
Classifier: Programming Language :: Python :: 3
Classifier: Programming Language :: Python :: 3.9
Classifier: Operating System :: POSIX :: Linux
Classifier: Topic :: System :: Hardware
Classifier: Topic :: Software Development :: Embedded Systems
Requires-Python: >=3.7
License-File: LICENSE
Requires-Dist: RPi.GPIO
Requires-Dist: Adafruit-Blinka
Requires-Dist: Pillow>=8.0.0
Requires-Dist: adafruit-blinka>=8.0.0
Dynamic: license-file
